zxcvbn_rs_py-0.2.0.dist-info/METADATA
zxcvbn_rs_py-0.2.0.dist-info/WHEEL
zxcvbn_rs_py-0.2.0.dist-info/licenses/LICENSE
zxcvbn_rs_py/zxcvbn_rs_py.pyi
zxcvbn_rs_py/__init__.py
zxcvbn_rs_py/py.typed
zxcvbn_rs_py/zxcvbn_rs_py.cpython-312-arm-linux-gnueabihf.so
zxcvbn_rs_py-0.2.0.dist-info/RECORD
