Metadata-Version: 2.4
Name: zxcvbn-rs-py
Version: 0.2.0
Classifier: Programming Language :: Rust
Classifier: Programming Language :: Python :: Implementation :: CPython
Classifier: Programming Language :: Python :: Implementation :: PyPy
Classifier: Topic :: Security
License-File: LICENSE
Summary: Python bindings for zxcvbn-rs, the Rust implementation of zxcvbn
Author-email: François Voron <contact@fief.dev>
Requires-Python: >=3.9, <3.14
Project-URL: Documentation, https://fief-dev.github.io/zxcvbn-rs-py/
Project-URL: Source, https://github.com/fief-dev/zxcvbn-rs-py
